Workbook

Sheet README
B1: SPECTRE-1 SCRATCH STORAGE — PRICING & COMPLIANCE MATRIX
B2: ORNL / UT-Battelle, LLC · Attachment C Technical Requirements v0.4 (May 2026) · Bldg 5300 DC-1N
B5: HOW TO USE THIS WORKBOOK
B6: Yellow cells | C6: Fill these in. Everything else is a formula, a label, or a pre-populated requirement — do not overwrite.
B7: Blue text | C7: A hardcoded input you entered.
B8: Black text | C8: A formula. It recalculates from your inputs.
B9: Grey italic row | C9: Example row showing the expected format. Delete or overwrite before submission.
B11: WHAT THE RFP ASKS FOR
B12: §1 Pricing breakouts | C12: "Pricing breakouts for all offered node types and relevant components." Use the 'Node & SSU Pricing' tab.
B13: §1 Three media options | C13: All-HDD, all-Flash, and hybrid must each be priced. Tag every line with its Config on the pricing tabs.
B14: §1 Adapter choice | C14: Price each high-speed network adapter option separately — see 'Network Adapters'.
B15: §1 Media capacity choice | C15: Price each drive capacity/technology option separately — see 'Media Options'.
B16: §1 Lead times | C16: The RFP explicitly wants part lead times so ORNL can trade scope against schedule. Fill the lead-time columns everywhere and summarize on 'Lead Time & Risk'.
B17: §3 Unmet requirements | C17: Any requirement not met must be identified with a discrepancy description, justification, and mitigation. Use the 'Compliance Matrix' tab.
B18: §3.2 50% floorspace | C18: The base bid occupies 8 of 16 production racks. Remaining footprint is priced as SSU growth options.
B19: §5 Support | C19: Four-year base, with separately priced 5th-year, 6th-year, and deferred-maintenance options — 'Support & Maintenance' tab.
B20: §5.5 Analyst | C20: The on-site System Software Analyst is separately priced and requires a DOE Q-clearance.
B22: HARD CONSTRAINTS TO CHECK EVERY LINE AGAINST
B23: Recording technology | C23: §3.2 bars HAMR, MAMR, and SMR. PMR/CMR only. Largest compliant drive is ~26 TB. Any HAMR/SMR line is non-compliant.
B24: FIPS SED on all media | C24: §3.2 requires FIPS 140-2 certified OR FIPS 140-3 compliant self-encrypting drives for ALL storage media, flash and disk.
B25: Power per rack | C25: 60 A / 208 VAC 3-phase = 17.3 kW usable per feed. Dual-fed diverse, so design to survive on ONE side: 17.3 kW/rack.
B26: Total power | C26: 275 kW cap across production + cluster management + 5300-DC TDS. The 8-rack base bid budget is ~138 kW.
B27: Rack envelope | C27: 17 racks total (16 production + 1 TDS), 600 mm wide, 50U usable. Extra-deep (1300 mm) cabinets permitted.
B28: TAA | C28: §3.1.6 requires TAA compliance on all hardware and software. HDD and NAND country-of-origin is the hard part — verify per part number.
B29: Uniform DIMMs | C29: §3.2 requires ECC DIMMs of a uniform FRU type across the system. One DIMM part number everywhere.
B30: Minimize node types | C30: §5.2 requires hot spare NODES of each type in the parts cache. Every additional node type multiplies spares cost.
B32: TABS
B33: Config Summary | C33: Roll-up of the three media configurations. Pulls from the pricing tabs — check it after every edit.
B34: Node & SSU Pricing | C34: Line-item pricing for every node and SSU type, tagged by config, with U, watts, lead time, TAA, FIPS.
B35: Media Options | C35: Drive-by-drive options. Includes the recording-technology and FIPS/TAA compliance gates.
B36: Network Adapters | C36: 400 GbE / Slingshot / InfiniBand / Ultra Ethernet options.
B37: TDS Pricing | C37: Per-TDS build. Two identical systems required (§3.2.1).
B38: Support & Maintenance | C38: Years 1-4 base plus 5th/6th year and deferred options. Quoted by the OEM per §5.
B39: Services & Deliverables | C39: Install, RDHX, and the full ATO/SCRM documentation package. Price these — do not absorb them.
B40: Lead Time & Risk | C40: Long-lead components and alternative delivery schedules per §1 and PPI §2.3.
B41: Compliance Matrix | C41: Pre-populated with the RFP's requirements. Mark Comply / Exception / Alternative on every row.
B43: Prepared for internal capture use. Verify every part number, FIPS status, and country of origin with the OEM before submission.

Sheet Config Summary
A1: CONFIG SUMMARY — three media strategies
A2: Capacity, power and price roll-up. Yellow cells are direct inputs; the rest pull from the pricing tabs.
A4: Metric | B4: Unit | C4: All-HDD | D4: All-Flash | E4: Hybrid (recommended) | F4: Constraint / target | G4: Pass?
A5: Usable capacity | B5: PB | F5: 150–250 PB (§3.2.2) — confirm 8-rack vs 16-rack | G5: =IF(MAX(C5:E5)=0,"—",IF(AND(MIN(C5:E5)>=150,MAX(C5:E5)<=250),"OK","CHECK"))
A6: Raw capacity | B6: PB | F6: —
A7: Erasure coding scheme | B7: text | F7: e.g. 8+2 declustered
A8: Storage efficiency | B8: % | C8: =IFERROR(C5/C6,0) | D8: =IFERROR(D5/D6,0) | E8: =IFERROR(E5/E6,0) | F8: usable ÷ raw
A9: Production racks used | B9: count | F9: 8 of 16 for base bid (§3.2)
A10: Rack U consumed | B10: U | F10: ≤ 50U per rack (§7)
A11: Total power draw | B11: kW | F11: ≤ 138 kW for 8-rack base; ≤ 275 kW all-in (§7.1) | G11: =IF(MAX(C11:E11)=0,"—",IF(MAX(C11:E11)<=138,"OK","OVER"))
A12: Power per rack | B12: kW | C12: =IFERROR(C11/C9,0) | D12: =IFERROR(D11/D9,0) | E12: =IFERROR(E11/E9,0) | F12: ≤ 17.3 kW on a single feed (§7.1) | G12: =IF(MAX(C12:E12)=0,"—",IF(MAX(C12:E12)<=17.3,"OK","OVER"))
A13: HSN endpoints | B13: count | F13: ≤ 120 (§3.2.2) | G13: =IF(MAX(C13:E13)=0,"—",IF(MAX(C13:E13)<=120,"OK","OVER"))
A14: Aggregate read bandwidth | B14: GB/s | F14: Offeror-stated, aged (§4, §4.2)
A15: Aggregate write bandwidth | B15: GB/s | F15: Offeror-stated, aged (§4, §4.2)
A16: Namespace IOPS (4 KiB) | B16: M IOPS | F16: Offeror-stated, aged (§4)
A17: mdtest file create rate | B17: K ops/s | F17: At 70% aged utilization (§4.2)
A18: Total inodes supported | B18: billions | F18: Plan for 10B (see brief §3.4)
A20: PRICE ROLL-UP
A21: Hardware subcontract — base bid (8 racks) | C21: =SUMIFS('Node & SSU Pricing'!$J$6:$J$61,'Node & SSU Pricing'!$B$6:$B$61,"All-HDD")+SUMIFS('Node & SSU Pricing'!$J$6:$J$61,'Node & SSU Pricing'!$B$6:$B$61,"All") | D21: =SUMIFS('Node & SSU Pricing'!$J$6:$J$61,'Node & SSU Pricing'!$B$6:$B$61,"All-Flash")+SUMIFS('Node & SSU Pricing'!$J$6:$J$61,'Node & SSU Pricing'!$B$6:$B$61,"All") | E21: =SUMIFS('Node & SSU Pricing'!$J$6:$J$61,'Node & SSU Pricing'!$B$6:$B$61,"Hybrid")+SUMIFS('Node & SSU Pricing'!$J$6:$J$61,'Node & SSU Pricing'!$B$6:$B$61,"All")
A22: Hardware subcontract — SSU growth options (racks 9–16)
A23: TDS — 2 systems | C23: ='TDS Pricing'!$H$20 | D23: ='TDS Pricing'!$H$20 | E23: ='TDS Pricing'!$H$20
A24: Services & deliverables (separately priced) | C24: ='Services & Deliverables'!$E$30 | D24: ='Services & Deliverables'!$E$30 | E24: ='Services & Deliverables'!$E$30
A25: Support & maintenance — years 1–4 | C25: =SUM('Support & Maintenance'!$D$22:$G$22)-SUM('Support & Maintenance'!$D$18:$G$18) | D25: =SUM('Support & Maintenance'!$D$22:$G$22)-SUM('Support & Maintenance'!$D$18:$G$18) | E25: =SUM('Support & Maintenance'!$D$22:$G$22)-SUM('Support & Maintenance'!$D$18:$G$18)
A26: Support & maintenance — year 5 option | C26: ='Support & Maintenance'!$H$22-'Support & Maintenance'!$H$18 | D26: ='Support & Maintenance'!$H$22-'Support & Maintenance'!$H$18 | E26: ='Support & Maintenance'!$H$22-'Support & Maintenance'!$H$18
A27: Support & maintenance — year 6 option | C27: ='Support & Maintenance'!$I$22-'Support & Maintenance'!$I$18 | D27: ='Support & Maintenance'!$I$22-'Support & Maintenance'!$I$18 | E27: ='Support & Maintenance'!$I$22-'Support & Maintenance'!$I$18
A28: On-site System Software Analyst (Q-cleared), 4 yr | C28: =SUM('Support & Maintenance'!$D$18:$G$18) | D28: =SUM('Support & Maintenance'!$D$18:$G$18) | E28: =SUM('Support & Maintenance'!$D$18:$G$18)
A30: TOTAL EVALUATED PRICE | C30: =SUM(C21:C28) | D30: =SUM(D21:D28) | E30: =SUM(E21:E28)
A32: $ per usable PB (hardware only) | C32: =IFERROR((C21+C22)/C5,0) | D32: =IFERROR((D21+D22)/D5,0) | E32: =IFERROR((E21+E22)/E5,0)
A35: Note: 'usable' must be defined in the proposal — post-erasure-code, post-filesystem-overhead, and before the 70% aged-utilization test of §4.2. Confirm whether ORNL's PB means 10^15 or PiB (2^50); the difference is 12.6%.

Sheet Node & SSU Pricing
A1: NODE & SSU PRICING
A2: §1: pricing breakouts for all offered node types and relevant components. Tag every line with the config it belongs to.
A4: ID | B4: Config | C4: Node / SSU type | D4: Description | E4: Mfr part no. | F4: Qty | G4: U each | H4: Watts each | I4: Unit price | J4: Extended price | K4: Total U | L4: Total kW | M4: Lead time (wks) | N4: TAA country of origin | O4: FIPS status | P4: Notes
A5: EX | B5: Hybrid | C5: Capacity SSU | D5: 4U102 JBOD, 102 x 26TB CMR SED | E5: 1EX2000-EXAMPLE | F5: 60 | G5: 4 | H5: 1300 | I5: 185000 | J5: =IFERROR(F5*I5,0) | K5: =IFERROR(F5*G5,0) | L5: =IFERROR(F5*H5/1000,0) | M5: 26 | N5: Thailand — verify | O5: 140-3 compliant SED | P5: Example row — overwrite
A6: 1 | J6: =IFERROR(F6*I6,0) | K6: =IFERROR(F6*G6,0) | L6: =IFERROR(F6*H6/1000,0)
A7: 2 | J7: =IFERROR(F7*I7,0) | K7: =IFERROR(F7*G7,0) | L7: =IFERROR(F7*H7/1000,0)
A8: 3 | J8: =IFERROR(F8*I8,0) | K8: =IFERROR(F8*G8,0) | L8: =IFERROR(F8*H8/1000,0)
A9: 4 | J9: =IFERROR(F9*I9,0) | K9: =IFERROR(F9*G9,0) | L9: =IFERROR(F9*H9/1000,0)
A10: 5 | J10: =IFERROR(F10*I10,0) | K10: =IFERROR(F10*G10,0) | L10: =IFERROR(F10*H10/1000,0)
A11: 6 | J11: =IFERROR(F11*I11,0) | K11: =IFERROR(F11*G11,0) | L11: =IFERROR(F11*H11/1000,0)
A12: 7 | J12: =IFERROR(F12*I12,0) | K12: =IFERROR(F12*G12,0) | L12: =IFERROR(F12*H12/1000,0)
A13: 8 | J13: =IFERROR(F13*I13,0) | K13: =IFERROR(F13*G13,0) | L13: =IFERROR(F13*H13/1000,0)
A14: 9 | J14: =IFERROR(F14*I14,0) | K14: =IFERROR(F14*G14,0) | L14: =IFERROR(F14*H14/1000,0)
A15: 10 | J15: =IFERROR(F15*I15,0) | K15: =IFERROR(F15*G15,0) | L15: =IFERROR(F15*H15/1000,0)
A16: 11 | J16: =IFERROR(F16*I16,0) | K16: =IFERROR(F16*G16,0) | L16: =IFERROR(F16*H16/1000,0)
A17: 12 | J17: =IFERROR(F17*I17,0) | K17: =IFERROR(F17*G17,0) | L17: =IFERROR(F17*H17/1000,0)
... A60: 55 | J60: =IFERROR(F60*I60,0) | K60: =IFERROR(F60*G60,0) | L60: =IFERROR(F60*H60/1000,0)
A62: TOTAL | J62: =SUM(J6:J61) | K62: =SUM(K6:K61) | L62: =SUM(L6:L61)
A64: Config values must be exactly: All-HDD, All-Flash, Hybrid, or All (for components common to every configuration). Config Summary sums on these strings.
A65: Every distinct node type here drives a hot-spare node in the §5.2 parts cache. Consolidating node types lowers both spares cost and TDS cost.

Sheet Media Options
A1: MEDIA OPTIONS
A2: §1 invites alternative HDD and flash technologies with lead times. §3.2 bars HAMR, MAMR and SMR, and requires FIPS SEDs on all media.
A4: ID | B4: Media type | C4: Mfr / model | D4: Part no. | E4: Capacity (TB) | F4: Recording tech | G4: Interface | H4: SED? | I4: FIPS status | J4: Country of origin | K4: TAA compliant? | L4: Watts (typ) | M4: Unit price | N4: $ per TB | O4: Lead time (wks) | P4: Endurance (DWPD) | Q4: Compliant? | R4: Notes
A5: EX | B5: HDD | C5: WD Ultrastar DC HC590 | D5: WUH722626AL5201 | E5: 26 | F5: ePMR / CMR | G5: SAS | H5: Y | I5: 140-3 compliant | J5: Thailand | K5: Verify | L5: 9 | M5: 620 | N5: =IFERROR(M5/E5,0) | O5: 26 | P5: n/a | Q5: =IF(C5="","",IF(OR(ISNUMBER(SEARCH("HAMR",F5)),ISNUMBER(SEARCH("MAMR",F5)),ISNUMBER(SEARCH("SMR",F5))),"NON-COMPLIANT",IF(H5<>"Y","NO SED",IF(K5="N","TAA FAIL","OK")))) | R5: Example row — overwrite. Largest CMR-compliant capacity available.
A6: 1 | N6: =IFERROR(M6/E6,0) | Q6: =IF(C6="","",IF(OR(ISNUMBER(SEARCH("HAMR",F6)),ISNUMBER(SEARCH("MAMR",F6)),ISNUMBER(SEARCH("SMR",F6))),"NON-COMPLIANT",IF(H6<>"Y","NO SED",IF(K6="N","TAA FAIL","OK"))))
A7: 2 | N7: =IFERROR(M7/E7,0) | Q7: =IF(C7="","",IF(OR(ISNUMBER(SEARCH("HAMR",F7)),ISNUMBER(SEARCH("MAMR",F7)),ISNUMBER(SEARCH("SMR",F7))),"NON-COMPLIANT",IF(H7<>"Y","NO SED",IF(K7="N","TAA FAIL","OK"))))
A8: 3 | N8: =IFERROR(M8/E8,0) | Q8: =IF(C8="","",IF(OR(ISNUMBER(SEARCH("HAMR",F8)),ISNUMBER(SEARCH("MAMR",F8)),ISNUMBER(SEARCH("SMR",F8))),"NON-COMPLIANT",IF(H8<>"Y","NO SED",IF(K8="N","TAA FAIL","OK"))))
A9: 4 | N9: =IFERROR(M9/E9,0) | Q9: =IF(C9="","",IF(OR(ISNUMBER(SEARCH("HAMR",F9)),ISNUMBER(SEARCH("MAMR",F9)),ISNUMBER(SEARCH("SMR",F9))),"NON-COMPLIANT",IF(H9<>"Y","NO SED",IF(K9="N","TAA FAIL","OK"))))
A10: 5 | N10: =IFERROR(M10/E10,0) | Q10: =IF(C10="","",IF(OR(ISNUMBER(SEARCH("HAMR",F10)),ISNUMBER(SEARCH("MAMR",F10)),ISNUMBER(SEARCH("SMR",F10))),"NON-COMPLIANT",IF(H10<>"Y","NO SED",IF(K10="N","TAA FAIL","OK"))))
A11: 6 | N11: =IFERROR(M11/E11,0) | Q11: =IF(C11="","",IF(OR(ISNUMBER(SEARCH("HAMR",F11)),ISNUMBER(SEARCH("MAMR",F11)),ISNUMBER(SEARCH("SMR",F11))),"NON-COMPLIANT",IF(H11<>"Y","NO SED",IF(K11="N","TAA FAIL","OK"))))
A12: 7 | N12: =IFERROR(M12/E12,0) | Q12: =IF(C12="","",IF(OR(ISNUMBER(SEARCH("HAMR",F12)),ISNUMBER(SEARCH("MAMR",F12)),ISNUMBER(SEARCH("SMR",F12))),"NON-COMPLIANT",IF(H12<>"Y","NO SED",IF(K12="N","TAA FAIL","OK"))))
A13: 8 | N13: =IFERROR(M13/E13,0) | Q13: =IF(C13="","",IF(OR(ISNUMBER(SEARCH("HAMR",F13)),ISNUMBER(SEARCH("MAMR",F13)),ISNUMBER(SEARCH("SMR",F13))),"NON-COMPLIANT",IF(H13<>"Y","NO SED",IF(K13="N","TAA FAIL","OK"))))
A14: 9 | N14: =IFERROR(M14/E14,0) | Q14: =IF(C14="","",IF(OR(ISNUMBER(SEARCH("HAMR",F14)),ISNUMBER(SEARCH("MAMR",F14)),ISNUMBER(SEARCH("SMR",F14))),"NON-COMPLIANT",IF(H14<>"Y","NO SED",IF(K14="N","TAA FAIL","OK"))))
A15: 10 | N15: =IFERROR(M15/E15,0) | Q15: =IF(C15="","",IF(OR(ISNUMBER(SEARCH("HAMR",F15)),ISNUMBER(SEARCH("MAMR",F15)),ISNUMBER(SEARCH("SMR",F15))),"NON-COMPLIANT",IF(H15<>"Y","NO SED",IF(K15="N","TAA FAIL","OK"))))
A16: 11 | N16: =IFERROR(M16/E16,0) | Q16: =IF(C16="","",IF(OR(ISNUMBER(SEARCH("HAMR",F16)),ISNUMBER(SEARCH("MAMR",F16)),ISNUMBER(SEARCH("SMR",F16))),"NON-COMPLIANT",IF(H16<>"Y","NO SED",IF(K16="N","TAA FAIL","OK"))))
A17: 12 | N17: =IFERROR(M17/E17,0) | Q17: =IF(C17="","",IF(OR(ISNUMBER(SEARCH("HAMR",F17)),ISNUMBER(SEARCH("MAMR",F17)),ISNUMBER(SEARCH("SMR",F17))),"NON-COMPLIANT",IF(H17<>"Y","NO SED",IF(K17="N","TAA FAIL","OK"))))
... A30: 25 | N30: =IFERROR(M30/E30,0) | Q30: =IF(C30="","",IF(OR(ISNUMBER(SEARCH("HAMR",F30)),ISNUMBER(SEARCH("MAMR",F30)),ISNUMBER(SEARCH("SMR",F30))),"NON-COMPLIANT",IF(H30<>"Y","NO SED",IF(K30="N","TAA FAIL","OK"))))
A32: Recording tech must read PMR or CMR for HDDs. The Compliant? column flags HAMR / MAMR / SMR automatically, per §3.2.
A33: FIPS status: enter '140-2 certified', '140-3 validated', '140-3 compliant', or 'none'. §3.2 accepts 140-2 certified OR 140-3 compliant SEDs. Note FIPS 140-2 certificates moved to historical status in 2026 — confirm ORNL still accepts them.
A34: Country of origin drives TAA (§3.1.6). HDD and NAND assembly frequently occurs in non-TAA-designated countries. Get a written country-of-origin statement per part number — do not assume.
A35: Endurance matters: scratch is write-heavy and churny. Confirm QLC DWPD covers the projected daily scratch turnover for the full 4–6 year PoP, or use TLC on the write-intensive tier.

Sheet Network Adapters
A1: NETWORK ADAPTER OPTIONS
A2: §1: 'Choice of network adapter.' §3.2 permits 400 GbE or equivalent — Ultra Ethernet, Slingshot, or InfiniBand.
A4: ID | B4: Fabric | C4: Mfr / model | D4: Part no. | E4: Ports/adapter | F4: Speed per port | G4: Watts each | H4: Unit price | I4: Qty | J4: Extended price | K4: Lead time (wks) | L4: TAA origin | M4: Notes
A5: EX | B5: 400 GbE | C5: Example NIC | D5: PN-EXAMPLE | E5: 2 | F5: 400 Gb/s | G5: 75 | H5: 3200 | I5: 30 | J5: =IFERROR(H5*I5,0) | K5: 20 | L5: Israel | M5: Example row — overwrite
A6: 1 | J6: =IFERROR(H6*I6,0)
A7: 2 | J7: =IFERROR(H7*I7,0)
A8: 3 | J8: =IFERROR(H8*I8,0)
A9: 4 | J9: =IFERROR(H9*I9,0)
A10: 5 | J10: =IFERROR(H10*I10,0)
A11: 6 | J11: =IFERROR(H11*I11,0)
A12: 7 | J12: =IFERROR(H12*I12,0)
A13: 8 | J13: =IFERROR(H13*I13,0)
A14: 9 | J14: =IFERROR(H14*I14,0)
A15: 10 | J15: =IFERROR(H15*I15,0)
A16: 11 | J16: =IFERROR(H16*I16,0)
A17: 12 | J17: =IFERROR(H17*I17,0)
... A20: 15 | J20: =IFERROR(H20*I20,0)
A22: TOTAL | J22: =SUM(J6:J20)
A24: Slingshot is HPE-proprietary. If SPECTRE-1's compute fabric is Slingshot, confirm third-party NIC availability and licensing before quoting a non-HPE storage platform against it.
A25: Ultra Ethernet silicon is early in 2026–27. If quoting UE, state firmware maturity and interoperability test evidence, and offer 400 GbE as the low-risk alternate.
A26: Endpoint count is capped at 120 (§3.2.2) but power caps it lower in practice — each 400G server costs roughly 1.1–1.2 kW against a ~138 kW base-bid budget.

Sheet TDS Pricing
A1: TEST & DEVELOPMENT SYSTEMS
A2: §3.2.1: two identical TDS, each a fully functional standalone system with a minimal set of every component in the production design.
A4: ID | B4: Component | C4: Description | D4: Qty per TDS | E4: Unit price | F4: Extended per TDS | G4: No. of TDS | H4: Total | I4: Lead time (wks) | J4: Notes
A5: 1 | B5: Metadata / management server | F5: =IFERROR(D5*E5,0) | G5: 2 | H5: =IFERROR(F5*G5,0)
A6: 2 | B6: Flash SSU (minimum viable) | F6: =IFERROR(D6*E6,0) | G6: 2 | H6: =IFERROR(F6*G6,0)
A7: 3 | B7: HDD SSU (minimum viable, hybrid only) | F7: =IFERROR(D7*E7,0) | G7: 2 | H7: =IFERROR(F7*G7,0)
A8: 4 | B8: Provisioning / cluster management server | F8: =IFERROR(D8*E8,0) | G8: 2 | H8: =IFERROR(F8*G8,0)
A9: 5 | B9: High-speed network adapters | F9: =IFERROR(D9*E9,0) | G9: 2 | H9: =IFERROR(F9*G9,0)
A10: 6 | B10: Top-of-rack management switching | F10: =IFERROR(D10*E10,0) | G10: 2 | H10: =IFERROR(F10*G10,0)
A11: 7 | B11: Cabinet, PDUs, rails | F11: =IFERROR(D11*E11,0) | G11: 2 | H11: =IFERROR(F11*G11,0)
A12: 8 | B12: Rear Door Heat Exchanger | F12: =IFERROR(D12*E12,0) | G12: 2 | H12: =IFERROR(F12*G12,0)
A13: 9 | B13: File system + HA + RHEL licensing | F13: =IFERROR(D13*E13,0) | G13: 2 | H13: =IFERROR(F13*G13,0)
A14: 10 | B14: Installation & integration | F14: =IFERROR(D14*E14,0) | G14: 2 | H14: =IFERROR(F14*G14,0)
A15: 11 | B15: Cabling & optics | F15: =IFERROR(D15*E15,0) | G15: 2 | H15: =IFERROR(F15*G15,0)
A20: TOTAL — BOTH TDS | H20: =SUM(H5:H15)
A22: One TDS occupies the 17th rack at 5300-DC and counts against the 275 kW cap. The second TDS location is not stated in Attachment C — submit a clarification question before pricing site work for it.
A23: §3.2.1: TDS support co-terminates with the production COMPUTE partition, not with this storage contract. Confirm that end date before pricing the support line.
A24: §5.2: TDS hardware may NOT be used as the spare parts cache. Price spares separately.

Sheet Support & Maintenance
A1: SUPPORT & MAINTENANCE
A2: §5 — quoted by the OEM. Four-year base with separately priced 5th-year, 6th-year and deferred-maintenance options.
A4: ID | B4: Item | C4: RFP ref | D4: Year 1 | E4: Year 2 | F4: Year 3 | G4: Year 4 | H4: Yr 5 (option) | I4: Yr 6 (option) | J4: Total
A5: 1 | B5: Hardware maintenance — production system | C5: §5 | J5: =SUM(D5:I5)
A6: 2 | B6: Hardware maintenance — TDS (x2) | C6: §3.2.1 | J6: =SUM(D6:I6)
A7: 3 | B7: File system software licensing & support | C7: §5.4 | J7: =SUM(D7:I7)
A8: 4 | B8: High-availability (HA) licensing | C8: §5.4 | J8: =SUM(D8:I8)
A9: 5 | B9: RHEL licensing & support | C9: §5 | J9: =SUM(D9:I9)
A10: 6 | B10: Quarterly system updates & security patching | C10: §5 | J10: =SUM(D10:I10)
A11: 7 | B11: Critical/High CVSS v4 remediation within 30 days | C11: §3.1.8 | J11: =SUM(D11:I11)
A12: 8 | B12: Remote technical support | C12: §5 | J12: =SUM(D12:I12)
A13: 9 | B13: On-site technical support | C13: §5 | J13: =SUM(D13:I13)
A14: 10 | B14: On-site parts cache — initial stocking | C14: §5.2 | J14: =SUM(D14:I14)
A15: 11 | B15: On-site parts cache — refresh | C15: §5.2 | J15: =SUM(D15:I15)
A16: 12 | B16: Hardware retention / no-return service (all FRUs) | C16: §5.3 | J16: =SUM(D16:I16)
... A18: 14 | B18: On-site System Software Analyst (DOE Q-cleared) | C18: §5.5 | J18: =SUM(D18:I18)
B20: Deferred maintenance option (§5.1) — describe & price | J20: =SUM(D20:I20)
B22: TOTALS | D22: =SUM(D5:D20) | E22: =SUM(E5:E20) | F22: =SUM(F5:F20) | G22: =SUM(G5:G20) | H22: =SUM(H5:H20) | I22: =SUM(I5:I20) | J22: =SUM(J5:J20)
B24: §5.1: years 5 and 6 must be priced at the standard four-year rate.
B25: §5.1: the maintenance period begins upon successful Acceptance (Q2CY2027), but the draft subcontract PoP starts 12/15/2026. Submit a clarification question and price to the answer.
B26: §5.3: no hardware leaves the site — ORNL destroys it. Every FRU needs a retention/no-return service, and you get no failure-analysis feedback, so size the parts cache conservatively.
B27: §5.2: the cache must sustain all repair actions for two weeks with no refresh, and must include hot spare NODES of every proposed type.
B28: §3.1.8 is a contractual SLA on third-party dependencies, not just your own code. In an air-gapped classified enclave, a 30-day patch cycle needs a defined media-transfer process — price the labor.

Sheet Services & Deliverables
A1: SERVICES & DELIVERABLES
A2: The documentation and services package. Price these explicitly — the ATO and SCRM artifacts alone are hundreds of hours.
A4: ID | B4: Deliverable | C4: RFP ref | D4: In hardware price? | E4: Separately priced | F4: Est. hours | G4: Owner | H4: Notes
A5: 1 | B5: Site Preparation Plan (within 30 days of award) | C5: §8.3
A6: 2 | B6: Maintenance & Support Plan (30 days before first delivery) | C6: §8.4
A7: 3 | B7: Proposed delivery / installation / acceptance schedule | C7: §8.2
A8: 4 | B8: Executive Liaison & Technical Project Manager assignment | C8: §8.2
A9: 5 | B9: Delivery, uncrating, inspection, staging, mounting, packaging removal | C9: §6, §7.2
A10: 6 | B10: RDHX supply, delivery, mounting, hose & control valve connection | C10: §7.2
A11: 7 | B11: Cable management — overhead electrical to equipment | C11: §7.1
A12: 8 | B12: Cable management — cabinet-to-cabinet network (optical/STP) | C12: §3.1.4, §7.1
A13: 9 | B13: Security Control Implementation Statements — all 800-53 High controls | C13: §3.1.13
A14: 10 | B14: System Security Plan (asset inventory, boundaries, network diagrams) | C14: §3.1.13
A15: 11 | B15: Configuration Management Plan | C15: §3.1.13
A16: 12 | B16: Incident Response Plan | C16: §3.1.13
... A28: 24 | B28: Activity Hazard Analysis (AHA) | C28: Attach. F
B30: TOTAL | E30: =SUM(E5:E28) | F30: =SUM(F5:F28)
B32: The RDHX scope (§7.2) is a mechanical contractor's work, not a storage OEM's. Identify the partner and price it before bid, including BACnet/IP integration and leak-detection commissioning.

Sheet Lead Time & Risk
A1: LEAD TIME & SCHEDULE RISK
A2: §1 invites alternative delivery schedules to mitigate long-lead risk. PPI §2.3 governs. Delivery Q1CY2027 / Acceptance Q2CY2027.
A4: ID | B4: Component | C4: Configs affected | D4: Quoted lead time (wks) | E4: Risk (H/M/L) | F4: Driver | G4: Mitigation / alternative schedule | H4: Notes
A5: 1 | B5: Nearline CMR HDDs (24–26 TB) | C5: All-HDD, Hybrid | F5: Nearline capacity heavily booked through 2026; CMR SKUs are a shrinking share of production as vendors shift to HAMR/SMR
A6: 2 | B6: High-capacity QLC NAND | C6: All-Flash, Hybrid | F6: NAND allocation and pricing pressure through 2026; the RFP itself cites long lead times for memory technologies
A7: 3 | B7: FIPS SED variants of top-capacity drives | C7: All | F7: SED/FIPS SKUs historically trail the leading capacity by a generation
A8: 4 | B8: DRAM (uniform ECC DIMM FRU) | C8: All | F8: Memory market conditions cited in §1
A9: 5 | B9: 400G NICs / Slingshot adapters | C9: All | F9: Fabric choice may be gated on the SPECTRE-1 compute award
A10: 6 | B10: Ultra Ethernet silicon | C10: All | F10: Early-generation availability and firmware maturity in 2026–27
A11: 7 | B11: Storage controllers / server platforms | C11: All | F11: Platform generation transition
A12: 8 | B12: Cabinets, PDUs (port-switchable, locking, watertight) | C12: All | F12: Non-standard PDU spec per §7.1
A13: 9 | B13: Rear Door Heat Exchangers | C13: All | F13: Custom spec: 1in sanitary, BACnet/IP, leak detect w/ shutdown, fail-closed
A14: 10 | B14: Optical cable & transceivers (inter-cabinet) | C14: All | F14: §3.1.4 forbids passive copper DAC between cabinets
B17: §1: 'Offerors can also propose alternative system delivery schedules to mitigate schedule risks.' A phased delivery — metadata and flash tier first, capacity tier second — protects the Q2CY2027 acceptance date and is worth offering explicitly.

Sheet Compliance Matrix
A1: COMPLIANCE MATRIX
A2: §3: any requirement not met must be identified with a discrepancy description, justification, and proposed mitigation or alternative.
A4: RFP § | B4: Requirement | C4: Comply / Exception / Alternative | D4: Evidence or reference | E4: Discrepancy & justification (required if Exception) | F4: Proposed mitigation / alternative | G4: Owner | H4: Status
A5: 3.1.1 | B5: NIST SP 800-53 Rev 5 High baseline, tailored for DoW systems
A6: 3.1.1 | B6: NIST SP 800-223 (HPC Security)
A7: 3.1.1 | B7: NIST SP 800-207 (Zero Trust Architecture)
A8: 3.1.1 | B8: NIST SP 800-216 (Vulnerability Disclosure)
A9: 3.1.1 | B9: NIST SP 800-193 (Platform Firmware Resiliency)
A10: 3.1.1 | B10: NIST SP 800-161 (Cybersecurity Supply Chain Risk)
A11: 3.1.1 | B11: FIPS 140-3 and SP 800-52 / 800-57 / 800-131A for cryptography
A12: 3.1.2 | B12: Data encrypted at rest
A13: 3.1.3 | B13: Data encrypted in transit where technically feasible; describe exceptions
A14: 3.1.4 | B14: All inter-cabinet cables optical or shielded twisted pair; intra-node optical preferred
A15: 3.1.5 | B15: FIPS 140-3 compliant and/or NSA-approved cryptographic algorithms
A16: 3.1.6 | B16: TAA compliance — all hardware, software and integrated components (19 U.S.C. 2501–2581)
... A67: 8.5 | B67: Benchmarks executable from a non-privileged account
B69: Enter exactly 'Comply', 'Exception', or 'Alternative' in column C. §3 requires that every Exception carry a discrepancy description, a justification, and a proposed mitigation or alternative — columns E and F are mandatory for those rows.
